django_eve_sde/__init__.py
django_eve_sde/industryActivity/__init__.py
django_eve_sde/industryActivity/models.py
django_eve_sde/industryActivityMaterials/__init__.py
django_eve_sde/industryActivityMaterials/models.py
django_eve_sde/industryActivityProducts/__init__.py
django_eve_sde/industryActivityProducts/models.py
django_eve_sde/invCategories/__init__.py
django_eve_sde/invCategories/models.py
django_eve_sde/invGroups/__init__.py
django_eve_sde/invGroups/models.py
django_eve_sde/invMarketGroups/__init__.py
django_eve_sde/invMarketGroups/models.py
django_eve_sde/invTypes/__init__.py
django_eve_sde/invTypes/models.py
django_eve_sde/management/__init__.py
django_eve_sde/management/commands/__init__.py
django_eve_sde/management/commands/update_sde.py
django_eve_sde/planetSchematics/__init__.py
django_eve_sde/planetSchematics/models.py
django_eve_sde/planetSchematicsPinMap/__init__.py
django_eve_sde/planetSchematicsPinMap/models.py
django_eve_sde/planetSchematicsTypeMap/__init__.py
django_eve_sde/planetSchematicsTypeMap/models.py
django_eve_sde-0.3.1.dist-info/METADATA
django_eve_sde-0.3.1.dist-info/WHEEL
django_eve_sde-0.3.1.dist-info/RECORD
