Metadata-Version: 2.3
Name: django-eve-sde
Version: 0.3.1
Summary: Something
License: MIT
Author: Tim Davis
Author-email: binary.god@gmail.com
Requires-Python: >=3.11,<4
Classifier: License :: OSI Approved :: MIT License
Classifier: Programming Language :: Python :: 3
Classifier: Programming Language :: Python :: 3.11
Classifier: Programming Language :: Python :: 3.12
Classifier: Programming Language :: Python :: 3.13
Requires-Dist: django (>=5.2.2,<6.0.0)
Requires-Dist: requests (>=2.32.3,<3.0.0)
